{
  "trailers": [
    {
      "id": "T000007844",
      "link": "https://www.youtube.com/watch?v=x--N03NO130",
      "release": "https://www.releases.com/p/frankenstein"
    },
    {
      "id": "T000007807",
      "link": "https://www.youtube.com/watch?v=sRqU2276eaQ",
      "release": "https://www.releases.com/p/wake-up-dead-man-a-knives-out-mystery"
    },
    {
      "id": "T000006136",
      "link": "https://www.youtube.com/watch?v=yNXK3mJQiNo",
      "release": "https://www.releases.com/p/eleanor-the-great"
    },
    {
      "id": "T000007665",
      "link": "https://www.youtube.com/watch?v=8YOEwDH6KP0"
    },
    {
      "id": "T000008779",
      "link": "https://www.youtube.com/watch?v=91VQzLK2wAU"
    },
    {
      "id": "T000008390",
      "link": "https://www.youtube.com/watch?v=Ia4PVP0qtO4"
    },
    {
      "id": "T000007676",
      "link": "https://www.youtube.com/watch?v=e3RSzFziCHo"
    },
    {
      "id": "T000008568",
      "link": "https://www.youtube.com/watch?v=fAye0rhqdU8"
    },
    {
      "id": "T000007769",
      "link": "https://www.youtube.com/watch?v=UMYlqN_zd2U"
    },
    {
      "id": "T000007926",
      "link": "https://www.youtube.com/watch?v=QNkoSFx2Qxg"
    },
    {
      "id": "T000009042",
      "link": "https://www.youtube.com/watch?v=Q1QW0kd4yuI"
    },
    {
      "id": "T000007893",
      "link": "https://www.youtube.com/watch?v=bNLWlWkVEIc"
    },
    {
      "id": "T000008257",
      "link": "https://www.youtube.com/watch?v=zP4diQVH7EE"
    },
    {
      "id": "T000007745",
      "link": "https://www.youtube.com/watch?v=zWQUztI-v58"
    },
    {
      "id": "T000008815",
      "link": "https://www.youtube.com/watch?v=vyqYw-Ba9aw"
    },
    {
      "id": "T000008527",
      "link": "https://www.youtube.com/watch?v=sfWhkp0-82A"
    },
    {
      "id": "T000007890",
      "link": "https://www.youtube.com/watch?v=iC2ciRMryyo"
    },
    {
      "id": "T000006569",
      "link": "https://www.youtube.com/watch?v=ZRFPYI8H6PE"
    },
    {
      "id": "T000006569",
      "link": "https://www.youtube.com/watch?v=ZRFPYI8H6PE"
    },
    {
      "id": "T000007659",
      "link": "https://www.youtube.com/watch?v=ZOsuDPzCTRg"
    },
    {
      "id": "T000007607",
      "link": "https://www.youtube.com/watch?v=Icznn-EoSfE"
    },
    {
      "id": "T000007664",
      "link": "https://www.youtube.com/watch?v=IkNXhI4Lteo"
    },
    {
      "id": "T000006387",
      "link": "https://www.youtube.com/watch?v=03sYnkxnFU4"
    },
    {
      "id": "T000007552",
      "link": "https://www.youtube.com/watch?v=DX0-t2T_2BY"
    },
    {
      "id": "T000006168",
      "link": "https://www.youtube.com/watch?v=MW9vEdJABEY"
    },
    {
      "id": "T000008217",
      "link": "https://www.youtube.com/watch?v=WFPrlEa294Q"
    },
    {
      "id": "T000007705",
      "link": "https://www.youtube.com/watch?v=EvzGTJM4gRg"
    },
    {
      "id": "T000008512",
      "link": "https://www.youtube.com/watch?v=Sxcrm1FGO9c"
    },
    {
      "id": "T000009092",
      "link": "https://www.youtube.com/watch?v=gEFxeMUzZaI"
    },
    {
      "id": "T000008517",
      "link": "https://www.youtube.com/watch?v=Yj4gJa0k7YE"
    },
    {
      "id": "T000007878",
      "link": "https://www.youtube.com/watch?v=Scm4ZzNCgRA"
    },
    {
      "id": "T000006464",
      "link": "https://www.youtube.com/watch?v=0xWuVI9ctvU"
    },
    {
      "id": "T000008378",
      "link": "https://www.youtube.com/watch?v=FgAB2fmzwjc"
    },
    {
      "id": "T000009012",
      "link": "https://www.youtube.com/watch?v=rW9Ene4sJ5o"
    },
    {
      "id": "T000006459",
      "link": "https://www.youtube.com/watch?v=yveaRkSkdtc"
    },
    {
      "id": "T000009023",
      "link": "https://www.youtube.com/watch?v=fefaxq2nXoE"
    },
    {
      "id": "T000008019",
      "link": "https://www.youtube.com/watch?v=ww-IXHXvS70"
    },
    {
      "id": "T000008520",
      "link": "https://www.youtube.com/watch?v=EveU3HbihvQ"
    },
    {
      "id": "T000007714",
      "link": "https://www.youtube.com/watch?v=aRpnP3LZ99g"
    },
    {
      "id": "T000007693",
      "link": "https://www.youtube.com/watch?v=HyRdazbYKgY"
    }
  ]
}
